LICENSE
MANIFEST.in
README.md
requirements.txt
setup.py
gears_react/__init__.py
gears_react/compiler.js
gears_react/compiler.py
gears_react.egg-info/PKG-INFO
gears_react.egg-info/SOURCES.txt
gears_react.egg-info/dependency_links.txt
gears_react.egg-info/requires.txt
gears_react.egg-info/top_level.txt
gears_react/node_modules/react-tools/README.md
gears_react/node_modules/react-tools/main.js
gears_react/node_modules/react-tools/package.json
gears_react/node_modules/react-tools/bin/jsx
gears_react/node_modules/react-tools/node_modules/.bin/commonize
gears_react/node_modules/react-tools/node_modules/commoner/.npmignore
gears_react/node_modules/react-tools/node_modules/commoner/.travis.yml
gears_react/node_modules/react-tools/node_modules/commoner/LICENSE
gears_react/node_modules/react-tools/node_modules/commoner/README.md
gears_react/node_modules/react-tools/node_modules/commoner/main.js
gears_react/node_modules/react-tools/node_modules/commoner/package.json
gears_react/node_modules/react-tools/node_modules/commoner/bin/commonize
gears_react/node_modules/react-tools/node_modules/commoner/node_modules/.bin/mkdirp
gears_react/node_modules/react-tools/node_modules/commoner/node_modules/commander/Readme.md
gears_react/node_modules/react-tools/node_modules/commoner/node_modules/commander/index.js
gears_react/node_modules/react-tools/node_modules/commoner/node_modules/commander/package.json
gears_react/node_modules/react-tools/node_modules/commoner/node_modules/glob/LICENSE
gears_react/node_modules/react-tools/node_modules/commoner/node_modules/glob/README.md
gears_react/node_modules/react-tools/node_modules/commoner/node_modules/glob/common.js
gears_react/node_modules/react-tools/node_modules/commoner/node_modules/glob/glob.js
gears_react/node_modules/react-tools/node_modules/commoner/node_modules/glob/package.json
gears_react/node_modules/react-tools/node_modules/commoner/node_modules/glob/sync.js
gears_react/node_modules/react-tools/node_modules/commoner/node_modules/glob/node_modules/inflight/.eslintrc
gears_react/node_modules/react-tools/node_modules/commoner/node_modules/glob/node_modules/inflight/LICENSE
