Metadata-Version: 1.1
Name: gears-react
Version: 0.2.2
Summary: Gears compiler for React/JSX
Home-page: https://github.com/mandx/gears-react
Author: Armando Perez Marques
Author-email: gmandx@gmail.com
License: ISC
Platform: UNKNOWN
Classifier: Development Status :: 3 - Alpha
Classifier: Intended Audience :: Developers
Classifier: Operating System :: OS Independent
Classifier: Programming Language :: Python
Classifier: Programming Language :: Python :: 2.7
Classifier: Programming Language :: Python :: 3.2
